linkkt_end/__init__.py
linkkt_end/core/__init__.py
linkkt_end/core/accessor.py
linkkt_end/core/creation.py
linkkt_end/data/__init__.py
linkkt_end/data/stochastic_generator.py
linkkt_end/handlers/__init__.py
linkkt_end/handlers/allocation.py
linkkt_end/handlers/exchange.py
linkkt_end/handlers/org_settings.py
linkkt_end/handlers/requirements.py
linkkt_end/handlers/sessions.py
linkkt_end/handlers/stoc_gen.py
linkkt_end/handlers/trades.py
linkkt_end/handlers/user.py
linkkt_end/handlers/files/__init__.py
linkkt_end/handlers/files/models/__init__.py
linkkt_end/stochastic/__init__.py
linkkt_end/stochastic/main.py
linkkt_end/stochastic/generators/__init__.py
linkkt_end/stochastic/generators/cox.py
linkkt_end/stochastic/generators/geometric_brownian.py
linkkt_end/stochastic/generators/heston.py
linkkt_end/stochastic/generators/jump_diffusion.py
linkkt_end/stochastic/generators/ornstien.py
linkkt_end/stochastic/utils/__init__.py
linkkt_end/stochastic/utils/main.py
linkkt_end/stochastic/utils/parameters.py
linkkt_end/utils/__init__.py
linkkt_end/utils/ordering.py
linkkt_end/utils/performance.py
linkkt_end/utils/tiingo_api.py
linkkt_end/utils/properties/__init__.py
linkkt_end/utils/properties/abstract.py
linkkt_end/utils/slippage/__init__.py
linkkt_end/utils/slippage/random_slippage.py
linkkt_end/utils/slippage/slippage_model.py
linkkt_end/utils/trades/__init__.py
linkkt_end/utils/trades/trade.py
linkkt_end/utils/trades/trade_pct.py
linkkt_end/utils/trades/trade_type.py
linkkt_end-0.2.5.dist-info/METADATA
linkkt_end-0.2.5.dist-info/WHEEL
linkkt_end-0.2.5.dist-info/top_level.txt
linkkt_end-0.2.5.dist-info/RECORD
