Metadata-Version: 2.1
Name: linkkt-end
Version: 0.2.5
Summary: Cross service interaction
Home-page: UNKNOWN
Author: Kevin Hill
Author-email: kah.kevin.hill@gmail.com
License: BSD
Keywords: example documentation tutorial
Platform: UNKNOWN
Classifier: Development Status :: 3 - Alpha
Classifier: Topic :: Utilities
Classifier: License :: OSI Approved :: BSD License
Requires-Dist: jamboree
Requires-Dist: mlfinlab
Requires-Dist: cvxpy
Requires-Dist: sklearn
Requires-Dist: cytoolz
Requires-Dist: loguru
Requires-Dist: maya
Requires-Dist: crayons
Requires-Dist: dask[dataframe]
